setup.py
pu_probability/Binomialdistribution.py
pu_probability/Gaussiandistribution.py
pu_probability/Generaldistribution.py
pu_probability/__init__.py
pu_probability.egg-info/PKG-INFO
pu_probability.egg-info/SOURCES.txt
pu_probability.egg-info/dependency_links.txt
pu_probability.egg-info/not-zip-safe
pu_probability.egg-info/top_level.txt