Metadata-Version: 1.0
Name: pu-probability
Version: 0.1
Summary: Gaussian and Binomial distributions
Home-page: UNKNOWN
Author: Priit Ulmas
Author-email: myemail@something.com
License: UNKNOWN
Platform: UNKNOWN
